uniharmony/__init__.py
uniharmony/__init__.pyi
uniharmony/_version.py
uniharmony/py.typed
uniharmony/combat/__init__.py
uniharmony/combat/__init__.pyi
uniharmony/combat/py.typed
uniharmony/dl/__init__.py
uniharmony/dl/__init__.pyi
uniharmony/dl/py.typed
uniharmony/interpolation/__init__.py
uniharmony/interpolation/__init__.pyi
uniharmony/interpolation/py.typed
uniharmony/normative/__init__.py
uniharmony/normative/__init__.pyi
uniharmony/normative/py.typed
uniharmony-0.0.0.dist-info/licenses/AUTHORS.rst
uniharmony-0.0.0.dist-info/licenses/LICENSE.md
uniharmony-0.0.0.dist-info/METADATA
uniharmony-0.0.0.dist-info/WHEEL
uniharmony-0.0.0.dist-info/top_level.txt
uniharmony-0.0.0.dist-info/RECORD
