Metadata-Version: 2.4
Name: uniharmony
Version: 0.0.0
Summary: Unified harmonization methods for machine and deep learning
Author-email: Nicolás Nieto <nnieto@sinc.unl.edu.ar>, Synchon Mandal <synchon@protonmail.com>
Maintainer-email: Synchon Mandal <synchon@protonmail.com>, Nicolás Nieto <nnieto@sinc.unl.edu.ar>
License: AGPL-3.0-only
Project-URL: Source, https://github.com/N-Nieto/UniHarmony
Classifier: Development Status :: 4 - Beta
Classifier: Environment :: Other Environment
Classifier: Intended Audience :: Developers
Classifier: Intended Audience :: Science/Research
Classifier: Intended Audience :: Education
Classifier: License :: OSI Approved
Classifier: Operating System :: OS Independent
Classifier: Programming Language :: Python :: 3
Classifier: Programming Language :: Python :: 3.10
Classifier: Programming Language :: Python :: 3.11
Classifier: Programming Language :: Python :: 3.12
Classifier: Programming Language :: Python :: 3.13
Classifier: Programming Language :: Python :: 3.14
Classifier: Topic :: Software Development
Classifier: Topic :: Scientific/Engineering
Classifier: Topic :: Utilities
Requires-Python: >=3.10
License-File: LICENSE.md
License-File: AUTHORS.rst
Requires-Dist: lazy_loader==0.4
Requires-Dist: structlog<26.0.0,>=25.0.0
Provides-Extra: dev
Requires-Dist: tox; extra == "dev"
Requires-Dist: pre-commit; extra == "dev"
Requires-Dist: ruff; extra == "dev"
Requires-Dist: towncrier; extra == "dev"
Dynamic: license-file
